discord_rest
