Metadata-Version: 2.1
Name: discord-rest
Version: 0.0.8
Summary: 🚀 A discord.py extension for Discord HTTP Interactions support.
Home-page: https://github.com/PranoyMajumdar/discord-ext-rest
Author: Pranoy Majumdar
Author-email: officialpranoy2@gmail.com
License: MIT
Project-URL: Homepage, https://github.com/PranoyMajumdar/discord-ext-rest
Classifier: Programming Language :: Python :: 3
Classifier: License :: OSI Approved :: MIT License
Classifier: Operating System :: OS Independent
Requires-Python: >=3.9
License-File: LICENSE
